Workbook

Sheet STUDENT GRADE 
A1: PR. 1 — Fundamental Booster | Student Data
A2: Student ID | B2: Name | C2: Math | D2: Science | E2: English | F2: Enrollment Date | G2: Student Grade | H2: Date of Birth | I2: Score | J2: Total Marks | K2: Percentage | L2: Age | M2: Math & Science >80 | P2: RESULT PREVIEW — Top students (Math > 80)
A3: 1001 | B3: Student 1 | C3: 61 | D3: 48 | E3: 76 | F3: 43101 | G3: =IF(C3>=80,"A",IF(C3>=60,"B",IF(C3>=40,"C","Fail"))) -> B | H3: 38579 | I3: =IF(C3>80,"Top Student","Normal") -> Normal | J3: =SUM(C3:E3) -> 185 | K3: =J3/300*100 -> 61.666667 | L3: =IF(H3="","",DATEDIF(H3,TODAY(),"Y")) -> 21 | M3: =IF(AND(C3>80,D3>80),"Yes","No") -> No | P3: Student ID | Q3: Name | R3: Math | S3: Science | T3: English | U3: Enrollment Date
A4: 1002 | B4: Student 2 | C4: 78 | D4: 76 | E4: 70 | F4: 43281 | G4: =IF(C4>=80,"A",IF(C4>=60,"B",IF(C4>=40,"C","Fail"))) -> B | H4: 38770 | I4: =IF(C4>80,"Top Student","Normal") -> Normal | J4: =SUM(C4:E4) -> 224 | K4: =J4/300*100 -> 74.666667 | L4: =IF(H4="","",DATEDIF(H4,TODAY(),"Y")) -> 20 | M4: =IF(AND(C4>80,D4>80),"Yes","No") -> No | P4: 1003 | Q4: Student 3 | R4: 97 | S4: 60 | T4: 51 | U4: 43461
A5: 1003 | B5: Student 3 | C5: 97 | D5: 60 | E5: 51 | F5: 43461 | G5: =IF(C5>=80,"A",IF(C5>=60,"B",IF(C5>=40,"C","Fail"))) -> A | H5: 38301 | I5: =IF(C5>80,"Top Student","Normal") -> Top Student | J5: =SUM(C5:E5) -> 208 | K5: =J5/300*100 -> 69.333333 | L5: =IF(H5="","",DATEDIF(H5,TODAY(),"Y")) -> 21 | M5: =IF(AND(C5>80,D5>80),"Yes","No") -> No | P5: 1008 | Q5: Student 8 | R5: 94 | S5: 67 | T5: 64 | U5: 44361
A6: 1004 | B6: Student 4 | C6: 74 | D6: 55 | E6: 46 | F6: 43641 | G6: =IF(C6>=80,"A",IF(C6>=60,"B",IF(C6>=40,"C","Fail"))) -> B | H6: 38477 | I6: =IF(C6>80,"Top Student","Normal") -> Normal | J6: =SUM(C6:E6) -> 175 | K6: =J6/300*100 -> 58.333333 | L6: =IF(H6="","",DATEDIF(H6,TODAY(),"Y")) -> 21 | M6: =IF(AND(C6>80,D6>80),"Yes","No") -> No | P6: 1010 | Q6: Student 10 | R6: 98 | S6: 54 | T6: 58 | U6: 44721
A7: 1005 | B7: Student 5 | C7: 68 | D7: 74 | E7: 84 | F7: 43821 | G7: =IF(C7>=80,"A",IF(C7>=60,"B",IF(C7>=40,"C","Fail"))) -> B | H7: 39069 | I7: =IF(C7>80,"Top Student","Normal") -> Normal | J7: =SUM(C7:E7) -> 226 | K7: =J7/300*100 -> 75.333333 | L7: =IF(H7="","",DATEDIF(H7,TODAY(),"Y")) -> 19 | M7: =IF(AND(C7>80,D7>80),"Yes","No") -> No | P7: 1012 | Q7: Student 12 | R7: 85 | S7: 89 | T7: 79 | U7: 45081
A8: 1006 | B8: Student 6 | C8: 80 | D8: 70 | E8: 65 | F8: 44001 | G8: =IF(C8>=80,"A",IF(C8>=60,"B",IF(C8>=40,"C","Fail"))) -> A | H8: 38542 | I8: =IF(C8>80,"Top Student","Normal") -> Normal | J8: =SUM(C8:E8) -> 215 | K8: =J8/300*100 -> 71.666667 | L8: =IF(H8="","",DATEDIF(H8,TODAY(),"Y")) -> 21 | M8: =IF(AND(C8>80,D8>80),"Yes","No") -> No | P8: 1013 | Q8: Student 13 | R8: 98 | S8: 90 | T8: 97 | U8: 45261
A9: 1007 | B9: Student 7 | C9: 75 | D9: 47 | E9: 78 | F9: 44181 | G9: =IF(C9>=80,"A",IF(C9>=60,"B",IF(C9>=40,"C","Fail"))) -> B | H9: 38073 | I9: =IF(C9>80,"Top Student","Normal") -> Normal | J9: =SUM(C9:E9) -> 200 | K9: =J9/300*100 -> 66.666667 | L9: =IF(H9="","",DATEDIF(H9,TODAY(),"Y")) -> 22 | M9: =IF(AND(C9>80,D9>80),"Yes","No") -> No | P9: 1014 | Q9: Student 14 | R9: 93 | S9: 40 | T9: 44 | U9: 45441
A10: 1008 | B10: Student 8 | C10: 94 | D10: 67 | E10: 64 | F10: 44361 | G10: =IF(C10>=80,"A",IF(C10>=60,"B",IF(C10>=40,"C","Fail"))) -> A | H10: 38729 | I10: =IF(C10>80,"Top Student","Normal") -> Top Student | J10: =SUM(C10:E10) -> 225 | K10: =J10/300*100 -> 75 | L10: =IF(H10="","",DATEDIF(H10,TODAY(),"Y")) -> 20 | M10: =IF(AND(C10>80,D10>80),"Yes","No") -> No | P10: 1016 | Q10: Student 16 | R10: 98 | S10: 77 | T10: 60 | U10: 45801
A11: 1009 | B11: Student 9 | C11: 41 | D11: 75 | E11: 56 | F11: 44541 | G11: =IF(C11>=80,"A",IF(C11>=60,"B",IF(C11>=40,"C","Fail"))) -> C | H11: 38625 | I11: =IF(C11>80,"Top Student","Normal") -> Normal | J11: =SUM(C11:E11) -> 172 | K11: =J11/300*100 -> 57.333333 | L11: =IF(H11="","",DATEDIF(H11,TODAY(),"Y")) -> 21 | M11: =IF(AND(C11>80,D11>80),"Yes","No") -> No | P11: 1018 | Q11: Student 18 | R11: 82 | S11: 48 | T11: 79 | U11: 46161
A12: 1010 | B12: Student 10 | C12: 98 | D12: 54 | E12: 58 | F12: 44721 | G12: =IF(C12>=80,"A",IF(C12>=60,"B",IF(C12>=40,"C","Fail"))) -> A | H12: 38091 | I12: =IF(C12>80,"Top Student","Normal") -> Top Student | J12: =SUM(C12:E12) -> 210 | K12: =J12/300*100 -> 70 | L12: =IF(H12="","",DATEDIF(H12,TODAY(),"Y")) -> 22 | M12: =IF(AND(C12>80,D12>80),"Yes","No") -> No | P12: 1019 | Q12: Student 19 | R12: 90 | S12: 78 | T12: 60 | U12: 46341
A13: 1011 | B13: Student 11 | C13: 73 | D13: 79 | E13: 53 | F13: 44901 | G13: =IF(C13>=80,"A",IF(C13>=60,"B",IF(C13>=40,"C","Fail"))) -> B | H13: 38876 | I13: =IF(C13>80,"Top Student","Normal") -> Normal | J13: =SUM(C13:E13) -> 205 | K13: =J13/300*100 -> 68.333333 | L13: =IF(H13="","",DATEDIF(H13,TODAY(),"Y")) -> 20 | M13: =IF(AND(C13>80,D13>80),"Yes","No") -> No | P13: 1020 | Q13: Student 20 | R13: 83 | S13: 92 | T13: 55 | U13: 46521
A14: 1012 | B14: Student 12 | C14: 85 | D14: 89 | E14: 79 | F14: 45081 | G14: =IF(C14>=80,"A",IF(C14>=60,"B",IF(C14>=40,"C","Fail"))) -> A | H14: 38650 | I14: =IF(C14>80,"Top Student","Normal") -> Top Student | J14: =SUM(C14:E14) -> 253 | K14: =J14/300*100 -> 84.333333 | L14: =IF(H14="","",DATEDIF(H14,TODAY(),"Y")) -> 20 | M14: =IF(AND(C14>80,D14>80),"Yes","No") -> Yes
A15: 1013 | B15: Student 13 | C15: 98 | D15: 90 | E15: 97 | F15: 45261 | G15: =IF(C15>=80,"A",IF(C15>=60,"B",IF(C15>=40,"C","Fail"))) -> A | H15: 38020 | I15: =IF(C15>80,"Top Student","Normal") -> Top Student | J15: =SUM(C15:E15) -> 285 | K15: =J15/300*100 -> 95 | L15: =IF(H15="","",DATEDIF(H15,TODAY(),"Y")) -> 22 | M15: =IF(AND(C15>80,D15>80),"Yes","No") -> Yes
A16: 1014 | B16: Student 14 | C16: 93 | D16: 40 | E16: 44 | F16: 45441 | G16: =IF(C16>=80,"A",IF(C16>=60,"B",IF(C16>=40,"C","Fail"))) -> A | H16: 38552 | I16: =IF(C16>80,"Top Student","Normal") -> Top Student | J16: =SUM(C16:E16) -> 177 | K16: =J16/300*100 -> 59 | L16: =IF(H16="","",DATEDIF(H16,TODAY(),"Y")) -> 21 | M16: =IF(AND(C16>80,D16>80),"Yes","No") -> No
A17: 1015 | B17: Student 15 | C17: 70 | D17: 51 | E17: 75 | F17: 45621 | G17: =IF(C17>=80,"A",IF(C17>=60,"B",IF(C17>=40,"C","Fail"))) -> B | H17: 39062 | I17: =IF(C17>80,"Top Student","Normal") -> Normal | J17: =SUM(C17:E17) -> 196 | K17: =J17/300*100 -> 65.333333 | L17: =IF(H17="","",DATEDIF(H17,TODAY(),"Y")) -> 19 | M17: =IF(AND(C17>80,D17>80),"Yes","No") -> No
A18: 1016 | B18: Student 16 | C18: 98 | D18: 77 | E18: 60 | F18: 45801 | G18: =IF(C18>=80,"A",IF(C18>=60,"B",IF(C18>=40,"C","Fail"))) -> A | H18: 38052 | I18: =IF(C18>80,"Top Student","Normal") -> Top Student | J18: =SUM(C18:E18) -> 235 | K18: =J18/300*100 -> 78.333333 | L18: =IF(H18="","",DATEDIF(H18,TODAY(),"Y")) -> 22 | M18: =IF(AND(C18>80,D18>80),"Yes","No") -> No
A19: 1017 | B19: Student 17 | C19: 66 | D19: 59 | E19: 40 | F19: 45981 | G19: =IF(C19>=80,"A",IF(C19>=60,"B",IF(C19>=40,"C","Fail"))) -> B | H19: 38493 | I19: =IF(C19>80,"Top Student","Normal") -> Normal | J19: =SUM(C19:E19) -> 165 | K19: =J19/300*100 -> 55 | L19: =IF(H19="","",DATEDIF(H19,TODAY(),"Y")) -> 21 | M19: =IF(AND(C19>80,D19>80),"Yes","No") -> No
A20: 1018 | B20: Student 18 | C20: 82 | D20: 48 | E20: 79 | F20: 46161 | G20: =IF(C20>=80,"A",IF(C20>=60,"B",IF(C20>=40,"C","Fail"))) -> A | H20: 38734 | I20: =IF(C20>80,"Top Student","Normal") -> Top Student | J20: =SUM(C20:E20) -> 209 | K20: =J20/300*100 -> 69.666667 | L20: =IF(H20="","",DATEDIF(H20,TODAY(),"Y")) -> 20 | M20: =IF(AND(C20>80,D20>80),"Yes","No") -> No
A21: 1019 | B21: Student 19 | C21: 90 | D21: 78 | E21: 60 | F21: 46341 | G21: =IF(C21>=80,"A",IF(C21>=60,"B",IF(C21>=40,"C","Fail"))) -> A | H21: 38228 | I21: =IF(C21>80,"Top Student","Normal") -> Top Student | J21: =SUM(C21:E21) -> 228 | K21: =J21/300*100 -> 76 | L21: =IF(H21="","",DATEDIF(H21,TODAY(),"Y")) -> 22 | M21: =IF(AND(C21>80,D21>80),"Yes","No") -> No
A22: 1020 | B22: Student 20 | C22: 83 | D22: 92 | E22: 55 | F22: 46521 | G22: =IF(C22>=80,"A",IF(C22>=60,"B",IF(C22>=40,"C","Fail"))) -> A | H22: 38690 | I22: =IF(C22>80,"Top Student","Normal") -> Top Student | J22: =SUM(C22:E22) -> 230 | K22: =J22/300*100 -> 76.666667 | L22: =IF(H22="","",DATEDIF(H22,TODAY(),"Y")) -> 20 | M22: =IF(AND(C22>80,D22>80),"Yes","No") -> Yes
A26: STUDENT TASK EXAMPLES | B26: Input / Criteria | C26: Result | D26: Notes
A27: COUNTIFS – Math above 50 | B27: >50 | C27: =COUNTIFS($C$3:$C$22,">50") -> 19 | D27: students
A28: COUNTIFS – Math above 60 | B28: >60 | C28: =COUNTIFS($C$3:$C$22,">60") -> 19 | D28: students
A29: AVERAGEIFS – Math above 60 | B29: >60 | C29: =AVERAGEIFS($C$3:$C$22,$C$3:$C$22,">60") -> 82.263158 | D29: Average Math score where Math >60
A30: VLOOKUP – Student name from ID | B30: 1006 | C30: =VLOOKUP(B30,$A$3:$B$22,2,FALSE) -> Student 6 | D30: Exact match: ID 1006
A31: Age – date of birth example | B31: 36753 | C31: =DATEDIF(B31,TODAY(),"Y") -> 26 | D31: Example only; DOB is not provided for students
A32: FILTER – Top-performing students | B32: Math > 80 | C32: See matching rows in the result preview below | D32: Full rows shown in result preview below

Sheet  SALES DATA 
A1: Sales ID | B1: Product Code | C1: Product | D1: Region | E1: Salesperson | F1: Amount | G1: Date | H1: Discount Rate | I1: Discount Type | J1: MONTH
A2: Column1 | B2: Column2 | C2: Column3 | D2: Column4 | E2: Column5 | F2: Column6 | G2: Column7 | H2: Column8 | I2: Column9 | J2: Column10
A3: 2001 | B3: PC101 | C3: Keyboard | D3: South | E3: Person 1 | F3: 7048 | G3: 44927 | H3: No Discount | I3: Not Eligible | J3: Jan | N3: RESULT PREVIEW — Sales tasks
A4: 2002 | B4: PC102 | C4: Printer | D4: West | E4: Person 2 | F4: 17428 | G4: 44942 | H4: 5% | I4: Eligible | J4: Jan | N4: Task | O4: Answer | P4: Meaning
A5: 2003 | B5: PC103 | C5: Mouse | D5: South | E5: Person 3 | F5: 23672 | G5: 44957 | H5: 10% | I5: Eligible | J5: Jan | N5: Column1 | O5: Column2 | P5: Column3
A6: 2004 | B6: PC104 | C6: Printer | D6: East | E6: Person 4 | F6: 5264 | G6: 44972 | H6: No Discount | I6: Not Eligible | J6: Feb | N6: SUMIFS — East + Mouse | O6: =' SALES DATA '!F16 -> 7283 | P6: Sum of matching sales amounts
A7: 2005 | B7: PC105 | C7: Keyboard | D7: North | E7: Person 5 | F7: 43388 | G7: 44987 | H7: 20% | I7: Eligible | J7: Mar | N7: VLOOKUP — PC110 amount | O7: =' SALES DATA '!F17 -> 15678 | P7: Product code PC110; returns Amount, not price
A8: 2006 | B8: PC106 | C8: Mouse | D8: North | E8: Person 6 | F8: 19757 | G8: 45002 | H8: 5% | I8: Eligible | J8: Mar | N8: INDEX/MATCH — Person 4 + Feb | O8: =' SALES DATA '!F18 -> 5277 | P8: Sales amount
A9: 2007 | B9: PC107 | C9: Mouse | D9: East | E9: Person 7 | F9: 32058 | G9: 45017 | H9: 10% | I9: Eligible | J9: Apr | N9: XLOOKUP — Person 12 amount | O9: =' SALES DATA '!F19 -> 41871 | P9: Sales amount
A10: 2008 | B10: PC108 | C10: Keyboard | D10: East | E10: Person 8 | F10: 46429 | G10: 45032 | H10: 20% | I10: Eligible | J10: Apr | N10: MATCH — first Mouse position | O10: =' SALES DATA '!F20 -> 38161 | P10: Position in Product list
A11: 2009 | B11: PC109 | C11: Printer | D11: East | E11: Person 9 | F11: 19746 | G11: 45047 | H11: 5% | I11: Eligible | J11: May | N11: INDIRECT — SUM(F3:F22) | O11: =' SALES DATA '!F21 -> 30436 | P11: Total sales amount
A12: 2010 | B12: PC110 | C12: Keyboard | D12: South | E12: Person 10 | F12: 35185 | G12: 45062 | H12: 10% | I12: Eligible | J12: May | N12: OFFSET — dynamic sales total | O12: =' SALES DATA '!F22 -> 33953 | P12: Sum of all Amount rows using OFFSET
A13: 2011 | B13: PC111 | C13: Keyboard | D13: East | E13: Person 11 | F13: 33920 | G13: 45077 | H13: 10% | I13: Eligible | J13: May
A14: 2012 | B14: PC112 | C14: Monitor | D14: North | E14: Person 12 | F14: 35611 | G14: 45092 | H14: 10% | I14: Eligible | J14: Jun
A15: 2013 | B15: PC113 | C15: Laptop | D15: East | E15: Person 13 | F15: 15560 | G15: 45107 | H15: 5% | I15: Eligible | J15: Jun
A16: 2014 | B16: PC114 | C16: Laptop | D16: South | E16: Person 14 | F16: 7283 | G16: 45122 | H16: 5% | I16: Eligible | J16: Jul | N16: Matching sales rows — East region + Mouse
A17: 2015 | B17: PC115 | C17: Laptop | D17: East | E17: Person 15 | F17: 15678 | G17: 45137 | H17: 5% | I17: Eligible | J17: Jul | N17: Sales ID | O17: Product Code | P17: Product | Q17: Region | R17: Salesperson | S17: Amount
A18: 2016 | B18: PC116 | C18: Mouse | D18: East | E18: Person 16 | F18: 5277 | G18: 45152 | H18: No Discount | I18: Not Eligible | J18: Aug | N18: 2007 | O18: PC107 | P18: Mouse | Q18: East | R18: Person 7 | S18: 32058
A19: 2017 | B19: PC117 | C19: Monitor | D19: North | E19: Person 17 | F19: 41871 | G19: 45167 | H19: 20% | I19: Eligible | J19: Aug | N19: 2016 | O19: PC116 | P19: Mouse | Q19: East | R19: Person 16 | S19: 5277
A20: 2018 | B20: PC118 | C20: Monitor | D20: West | E20: Person 18 | F20: 38161 | G20: 45182 | H20: 10% | I20: Eligible | J20: Sep
A21: 2019 | B21: PC119 | C21: Mouse | D21: West | E21: Person 19 | F21: 30436 | G21: 45197 | H21: 10% | I21: Eligible | J21: Sep
A22: 2020 | B22: PC120 | C22: Printer | D22: West | E22: Person 20 | F22: 33953 | G22: 45212 | H22: 10% | I22: Eligible | J22: Oct
A24: SALES TASK EXAMPLES | B24: Input 1 | C24: Input 2 | D24: Formula / Result | E24: Result Check
A25: Column1 | B25: Column2 | C25: Column3 | D25: Column4 | E25: Column5
A26: SUMIFS – East region + Mouse | B26: East | C26: Mouse | D26: =SUMIFS('[1]Sales Data'!$F$3:$F$22,'[1]Sales Data'!$D$3:$D$22,B26,'[1]Sales Data'!$C$3:$C$22,C26) -> #VALUE! | E26: Expected total
A27: VLOOKUP – Amount by product code | B27: PC110 | D27: =VLOOKUP(B27,'[1]Sales Data'!$B$3:$F$22,5,FALSE) -> 35185 | E27: Exact match; amount column is 5th in B:F
A28: INDEX/MATCH – salesperson + month | B28: Person 4 | C28: Feb | D28: =INDEX('[1]Sales Data'!$F$3:$F$22,MATCH(1,('[1]Sales Data'!$E$3:$E$22=B28)*('[1]Sales Data'!$J$3:$J$22=C28),0)) -> #VALUE! | E28: Excel 365/2021 array formula
A29: XLOOKUP – salesperson amount | B29: Person 12 | D29: =_xludf.XLOOKUP(B29,'[1]Sales Data'!$E$3:$E$22,'[1]Sales Data'!$F$3:$F$22,"Not found") -> #NAME? | E29: Exact match
A30: MATCH – product position | B30: Mouse | D30: =MATCH(B30,'[1]Sales Data'!$C$3:$C$22,0) -> 3 | E30: First occurrence position
A31: INDIRECT – range to total | B31: F3:F22 | D31: =SUM(INDIRECT(B31)) -> 507725 | E31: Range text is in M8
A32: OFFSET – dynamic sales total | D32: =SUM(OFFSET('[1]Sales Data'!$F$3,0,0,COUNTA('[1]Sales Data'!$F$3:$F$22),1)) -> #VALUE! | E32: Sum current Amount rows
A33: Date difference in days | B33: 44927 | C33: 44942 | D33: =DATEDIF(B33,C33,"d") -> 15 | E33: 15 days
A34: ROUND – Amount to whole rupee | B34: F3 | D34: =ROUND('[1]Sales Data'!F3,0) -> 7048 | E34: Uses first sales amount
A35: CEILING – Next 1,000 | B35: F3 | D35: =CEILING('[1]Sales Data'!F3,1000) -> 8000 | E35: Rounds up to next 1,000

Sheet  EMPLOYEES DATA 
A1: Employee ID | B1: Name | C1: Department | D1: Salary | E1: Joining Date | F1: Days Since Joining | G1: First Name | H1: UPPER Name | I1: lower Name
A2: 3001 | B2: Employee 1 | C2: Finance | D2: 86766 | E2: 42005 | F2: =IF(E2>TODAY(),"Not joined yet",TODAY()-E2) -> 4312 | G2: =LEFT(B2,FIND(" ",B2&" ")-1) -> Employee | H2: =UPPER(B2) -> EMPLOYEE 1 | I2: =LOWER(B2) -> employee 1 | K2: RESULT PREVIEW — Employee tasks
A3: 3002 | B3: Employee 2 | C3: Finance | D3: 31943 | E3: 42255 | F3: =IF(E3>TODAY(),"Not joined yet",TODAY()-E3) -> 4062 | G3: =LEFT(B3,FIND(" ",B3&" ")-1) -> Employee | H3: =UPPER(B3) -> EMPLOYEE 2 | I3: =LOWER(B3) -> employee 2 | K3: Task | L3: Answer | M3: Details
A4: 3003 | B4: Employee 3 | C4: HR | D4: 63374 | E4: 42505 | F4: =IF(E4>TODAY(),"Not joined yet",TODAY()-E4) -> 3812 | G4: =LEFT(B4,FIND(" ",B4&" ")-1) -> Employee | H4: =UPPER(B4) -> EMPLOYEE 3 | I4: =LOWER(B4) -> employee 3 | K4: XLOOKUP — ID 3007 salary | L4: 35960 | M4: Employee 7
A5: 3004 | B5: Employee 4 | C5: Finance | D5: 109972 | E5: 42755 | F5: =IF(E5>TODAY(),"Not joined yet",TODAY()-E5) -> 3562 | G5: =LEFT(B5,FIND(" ",B5&" ")-1) -> Employee | H5: =UPPER(B5) -> EMPLOYEE 4 | I5: =LOWER(B5) -> employee 4 | K5: INDEX/MATCH — ID 3007 salary | L5: 35960 | M5: Same result using INDEX + MATCH
A6: 3005 | B6: Employee 5 | C6: IT | D6: 54149 | E6: 43005 | F6: =IF(E6>TODAY(),"Not joined yet",TODAY()-E6) -> 3312 | G6: =LEFT(B6,FIND(" ",B6&" ")-1) -> Employee | H6: =UPPER(B6) -> EMPLOYEE 5 | I6: =LOWER(B6) -> employee 5 | K6: LEFT — First name | L6: Employee | M6: Employee 7
A7: 3006 | B7: Employee 6 | C7: IT | D7: 78689 | E7: 43255 | F7: =IF(E7>TODAY(),"Not joined yet",TODAY()-E7) -> 3062 | G7: =LEFT(B7,FIND(" ",B7&" ")-1) -> Employee | H7: =UPPER(B7) -> EMPLOYEE 6 | I7: =LOWER(B7) -> employee 6 | K7: UPPER — Name | L7: EMPLOYEE 7 | M7: Employee 7
A8: 3007 | B8: Employee 7 | C8: Marketing | D8: 35960 | E8: 43505 | F8: =IF(E8>TODAY(),"Not joined yet",TODAY()-E8) -> 2812 | G8: =LEFT(B8,FIND(" ",B8&" ")-1) -> Employee | H8: =UPPER(B8) -> EMPLOYEE 7 | I8: =LOWER(B8) -> employee 7 | K8: LOWER — Name | L8: employee 7 | M8: Employee 7
A9: 3008 | B9: Employee 8 | C9: IT | D9: 91659 | E9: 43755 | F9: =IF(E9>TODAY(),"Not joined yet",TODAY()-E9) -> 2562 | G9: =LEFT(B9,FIND(" ",B9&" ")-1) -> Employee | H9: =UPPER(B9) -> EMPLOYEE 8 | I9: =LOWER(B9) -> employee 8
A10: 3009 | B10: Employee 9 | C10: IT | D10: 90423 | E10: 44005 | F10: =IF(E10>TODAY(),"Not joined yet",TODAY()-E10) -> 2312 | G10: =LEFT(B10,FIND(" ",B10&" ")-1) -> Employee | H10: =UPPER(B10) -> EMPLOYEE 9 | I10: =LOWER(B10) -> employee 9
A11: 3010 | B11: Employee 10 | C11: HR | D11: 107877 | E11: 44255 | F11: =IF(E11>TODAY(),"Not joined yet",TODAY()-E11) -> 2062 | G11: =LEFT(B11,FIND(" ",B11&" ")-1) -> Employee | H11: =UPPER(B11) -> EMPLOYEE 10 | I11: =LOWER(B11) -> employee 10
A12: 3011 | B12: Employee 11 | C12: Finance | D12: 107634 | E12: 44505 | F12: =IF(E12>TODAY(),"Not joined yet",TODAY()-E12) -> 1812 | G12: =LEFT(B12,FIND(" ",B12&" ")-1) -> Employee | H12: =UPPER(B12) -> EMPLOYEE 11 | I12: =LOWER(B12) -> employee 11
A13: 3012 | B13: Employee 12 | C13: Finance | D13: 35226 | E13: 44755 | F13: =IF(E13>TODAY(),"Not joined yet",TODAY()-E13) -> 1562 | G13: =LEFT(B13,FIND(" ",B13&" ")-1) -> Employee | H13: =UPPER(B13) -> EMPLOYEE 12 | I13: =LOWER(B13) -> employee 12
A14: 3013 | B14: Employee 13 | C14: HR | D14: 40872 | E14: 45005 | F14: =IF(E14>TODAY(),"Not joined yet",TODAY()-E14) -> 1312 | G14: =LEFT(B14,FIND(" ",B14&" ")-1) -> Employee | H14: =UPPER(B14) -> EMPLOYEE 13 | I14: =LOWER(B14) -> employee 13
A15: 3014 | B15: Employee 14 | C15: HR | D15: 55378 | E15: 45255 | F15: =IF(E15>TODAY(),"Not joined yet",TODAY()-E15) -> 1062 | G15: =LEFT(B15,FIND(" ",B15&" ")-1) -> Employee | H15: =UPPER(B15) -> EMPLOYEE 14 | I15: =LOWER(B15) -> employee 14
A16: 3015 | B16: Employee 15 | C16: HR | D16: 63297 | E16: 45505 | F16: =IF(E16>TODAY(),"Not joined yet",TODAY()-E16) -> 812 | G16: =LEFT(B16,FIND(" ",B16&" ")-1) -> Employee | H16: =UPPER(B16) -> EMPLOYEE 15 | I16: =LOWER(B16) -> employee 15
A17: 3016 | B17: Employee 16 | C17: Finance | D17: 114173 | E17: 45755 | F17: =IF(E17>TODAY(),"Not joined yet",TODAY()-E17) -> 562 | G17: =LEFT(B17,FIND(" ",B17&" ")-1) -> Employee | H17: =UPPER(B17) -> EMPLOYEE 16 | I17: =LOWER(B17) -> employee 16
A18: 3017 | B18: Employee 17 | C18: HR | D18: 86915 | E18: 46005 | F18: =IF(E18>TODAY(),"Not joined yet",TODAY()-E18) -> 312 | G18: =LEFT(B18,FIND(" ",B18&" ")-1) -> Employee | H18: =UPPER(B18) -> EMPLOYEE 17 | I18: =LOWER(B18) -> employee 17
A19: 3018 | B19: Employee 18 | C19: IT | D19: 116284 | E19: 46255 | F19: =IF(E19>TODAY(),"Not joined yet",TODAY()-E19) -> 62 | G19: =LEFT(B19,FIND(" ",B19&" ")-1) -> Employee | H19: =UPPER(B19) -> EMPLOYEE 18 | I19: =LOWER(B19) -> employee 18
A20: 3019 | B20: Employee 19 | C20: Marketing | D20: 116283 | E20: 46505 | F20: =IF(E20>TODAY(),"Not joined yet",TODAY()-E20) -> Not joined yet | G20: =LEFT(B20,FIND(" ",B20&" ")-1) -> Employee | H20: =UPPER(B20) -> EMPLOYEE 19 | I20: =LOWER(B20) -> employee 19
A21: 3020 | B21: Employee 20 | C21: Marketing | D21: 99924 | E21: 46755 | F21: =IF(E21>TODAY(),"Not joined yet",TODAY()-E21) -> Not joined yet | G21: =LEFT(B21,FIND(" ",B21&" ")-1) -> Employee | H21: =UPPER(B21) -> EMPLOYEE 20 | I21: =LOWER(B21) -> employee 20
A25: EMPLOYEE TASK EXAMPLES | B25: Input | C25: Result | D25: Notes | G25: Employee text-function preview | H25: Column1 | I25: Column2 | J25: Column3 | K25: Column4
A26: Employee ID lookup | B26: 3007 | C26: =_xludf.XLOOKUP(B26,$A$3:$A$22,$D$3:$D$22,"Not found") -> #NAME? | D26: Returns salary | G26: Employee ID | H26: Original Name | I26: First Name | J26: UPPER Name | K26: lower Name
A27: Return field | B27: Salary | C27: Use XLOOKUP or INDEX/MATCH | D27: Return column is Salary | G27: 3001 | H27: Employee 1 | I27: =C11 -> HR | J27: =D11 -> 107877 | K27: =E11 -> 44255
A28: INDEX/MATCH – salary by ID | B28: 3007 | C28: =INDEX($D$3:$D$22,MATCH(B28,$A$3:$A$22,0)) -> 35960 | D28: Returns ₹35,960 | G28: 3002 | H28: Employee 2 | I28: =C12 -> Finance | J28: =D12 -> 107634 | K28: =E12 -> 44505
G29: 3003 | H29: Employee 3 | I29: =C13 -> Finance | J29: =D13 -> 35226 | K29: =E13 -> 44755
G30: 3004 | H30: Employee 4 | I30: =C14 -> HR | J30: =D14 -> 40872 | K30: =E14 -> 45005
G31: 3005 | H31: Employee 5 | I31: =C15 -> HR | J31: =D15 -> 55378 | K31: =E15 -> 45255
G32: 3006 | H32: Employee 6 | I32: =C16 -> HR | J32: =D16 -> 63297 | K32: =E16 -> 45505
G33: 3007 | H33: Employee 7 | I33: =C17 -> Finance | J33: =D17 -> 114173 | K33: =E17 -> 45755
G34: 3008 | H34: Employee 8 | I34: =C18 -> HR | J34: =D18 -> 86915 | K34: =E18 -> 46005
G35: 3009 | H35: Employee 9 | I35: =C19 -> IT | J35: =D19 -> 116284 | K35: =E19 -> 46255
G36: 3010 | H36: Employee 10 | I36: =C20 -> Marketing | J36: =D20 -> 116283 | K36: =E20 -> 46505
G37: 3011 | H37: Employee 11 | I37: =C21 -> Marketing | J37: =D21 -> 99924 | K37: =E21 -> 46755
G38: 3012 | H38: Employee 12 | I38: =C22 -> 0 | J38: =D22 -> 0 | K38: =E22 -> 0
G39: 3013 | H39: Employee 13 | I39: =C23 -> 0 | J39: =D23 -> 0 | K39: =E23 -> 0
G40: 3014 | H40: Employee 14 | I40: =C24 -> 0 | J40: =D24 -> 0 | K40: =E24 -> 0
... G46: 3020 | H46: Employee 20 | I46: =C30 -> 0 | J46: =D30 -> 0 | K46: =E30 -> 0
